decos/__init__.py
decos/decos.py
decos-0.0.12.post10.dist-info/LICENSE
decos-0.0.12.post10.dist-info/METADATA
decos-0.0.12.post10.dist-info/WHEEL
decos-0.0.12.post10.dist-info/top_level.txt
decos-0.0.12.post10.dist-info/RECORD
