Metadata-Version: 2.1
Name: decos
Version: 0.0.12.post10
Summary: some decorators
Home-page: https://github.com/shang-vikas/decos
Author: Vikas Sangwan
Author-email: 16vikas96@gmail.com
License: UNKNOWN
Platform: UNKNOWN
Classifier: Programming Language :: Python :: 3
Classifier: License :: OSI Approved :: MIT License
Classifier: Operating System :: OS Independent
